dmake/__init__.py
dmake/aws.py
dmake/azure.py
dmake/base_commands.py
dmake/cmd.py
dmake/command_registry.py
dmake/common.py
dmake/config.py
dmake/deploy.py
dmake/doc.py
dmake/release.py
dmake/stack.py
dmake/status.py
dmake_hms-0.1.31.dist-info/METADATA
dmake_hms-0.1.31.dist-info/WHEEL
dmake_hms-0.1.31.dist-info/entry_points.txt
dmake_hms-0.1.31.dist-info/top_level.txt
dmake_hms-0.1.31.dist-info/RECORD
