Metadata-Version: 2.4
Name: dmake-hms
Version: 0.1.31
Summary: A Docker+Swarm-based CI toolset frontend
Author-email: NumeriCube <support@numericube.com>
License: GPL-2
Project-URL: Homepage, https://dmake.org
Project-URL: Source, https://github.com/numericube/dmake
Project-URL: Documentation, https://github.com/numericube/dmake
Project-URL: BugTracker, https://github.com/numericube/dmake
Requires-Python: >=3.6
Requires-Dist: ruamel.yaml>=0.16.10
